dcustat/__init__.py
dcustat/__main__.py
dcustat/cli.py
dcustat/core.py
dcustat/rocm_smi.py
dcustat-0.0.3.dist-info/LICENSE
dcustat-0.0.3.dist-info/METADATA
dcustat-0.0.3.dist-info/WHEEL
dcustat-0.0.3.dist-info/entry_points.txt
dcustat-0.0.3.dist-info/top_level.txt
dcustat-0.0.3.dist-info/RECORD
