Metadata-Version: 2.1
Name: dcustat
Version: 0.0.3
Summary: An utility to monitor Hygon DCU status and usage
Home-page: https://github.com/wmc1992/dcustat
Author: wmc1992
Author-email: m18810541081@163.com
License: MIT
Keywords: dcu monitoring dcustat
Platform: UNKNOWN
Classifier: License :: OSI Approved :: MIT License
Classifier: Operating System :: POSIX :: Linux
Classifier: Programming Language :: Python :: 3
Classifier: Topic :: System :: Monitoring
Requires-Python: >=3.8
License-File: LICENSE
Requires-Dist: six (>=1.7)
Requires-Dist: blessed (>=1.17.1)
